lib/__init__.py
lib/ok.py
sscd6-3.3.3.dist-info/METADATA
sscd6-3.3.3.dist-info/WHEEL
sscd6-3.3.3.dist-info/top_level.txt
sscd6-3.3.3.dist-info/RECORD
